rtrie/__init__.py
rtrie/__main__.py
rtrie/array_trie.py
rtrie/naive_trie.py
rtrie/node.py
rtrie/stats.py
rtrie/stored_trie.py
rtrie/string_trie.py
rtrie/trie.py
rtrie/types.py
rtrie-1.0.1.dist-info/METADATA
rtrie-1.0.1.dist-info/WHEEL
rtrie-1.0.1.dist-info/RECORD
