Metadata-Version: 2.1
Name: rtrie
Version: 1.0.1
Summary: 
License: MIT
Author: alexgagnon
Author-email: alex@monad.media
Requires-Python: >=3.11,<4.0
Classifier: License :: OSI Approved :: MIT License
Classifier: Programming Language :: Python :: 3
Classifier: Programming Language :: Python :: 3.11
Classifier: Programming Language :: Python :: 3.12
Requires-Dist: argparse (>=1.4.0,<2.0.0)
Requires-Dist: rapidfuzz (>=3.1.1,<4.0.0)
